nonebot_plugin_resolver2/__init__.py
nonebot_plugin_resolver2/config.py
nonebot_plugin_resolver2/constants.py
nonebot_plugin_resolver2/cookie.py
nonebot_plugin_resolver2/download/__init__.py
nonebot_plugin_resolver2/download/utils.py
nonebot_plugin_resolver2/download/ytdlp.py
nonebot_plugin_resolver2/exception.py
nonebot_plugin_resolver2/matchers/__init__.py
nonebot_plugin_resolver2/matchers/acfun.py
nonebot_plugin_resolver2/matchers/bilibili.py
nonebot_plugin_resolver2/matchers/douyin.py
nonebot_plugin_resolver2/matchers/filter.py
nonebot_plugin_resolver2/matchers/helper.py
nonebot_plugin_resolver2/matchers/kuaishou.py
nonebot_plugin_resolver2/matchers/preprocess.py
nonebot_plugin_resolver2/matchers/tiktok.py
nonebot_plugin_resolver2/matchers/twitter.py
nonebot_plugin_resolver2/matchers/weibo.py
nonebot_plugin_resolver2/matchers/xiaohongshu.py
nonebot_plugin_resolver2/matchers/ytb.py
nonebot_plugin_resolver2/parsers/__init__.py
nonebot_plugin_resolver2/parsers/acfun.py
nonebot_plugin_resolver2/parsers/bilibili.py
nonebot_plugin_resolver2/parsers/data.py
nonebot_plugin_resolver2/parsers/douyin.py
nonebot_plugin_resolver2/parsers/kuaishou.py
nonebot_plugin_resolver2/parsers/twitter.py
nonebot_plugin_resolver2/parsers/utils.py
nonebot_plugin_resolver2/parsers/weibo.py
nonebot_plugin_resolver2/parsers/xiaohongshu.py
nonebot_plugin_resolver2/utils.py
nonebot_plugin_resolver2-1.13.1.dist-info/WHEEL
nonebot_plugin_resolver2-1.13.1.dist-info/METADATA
nonebot_plugin_resolver2-1.13.1.dist-info/RECORD
