Metadata-Version: 2.3
Name: nonebot-plugin-resolver2
Version: 1.13.1
Summary: NoneBot2 链接分享自动解析 ob 版, 支持 B站/抖音/快手/微博/小红书/youtube/tiktok/twitter/acfun
Keywords: nonebot,nonebot2,resolver,bilibili,youtube,tiktok,twitter
Author: fllesser
Author-email: fllesser <fllessive@gmail.com>
Requires-Dist: msgspec>=0.19.0,<1.0.0
Requires-Dist: httpx>=0.27.2,<1.0.0
Requires-Dist: curl-cffi>=0.13.0,<1.0.0
Requires-Dist: tqdm>=4.67.1,<5.0.0
Requires-Dist: aiofiles>=24.1.0
Requires-Dist: yt-dlp>=2025.9.26
Requires-Dist: nonebot2>=2.4.3,<3.0.0
Requires-Dist: nonebot-adapter-onebot>=2.4.6,<3.0.0
Requires-Dist: nonebot-plugin-localstore>=0.7.4,<1.0.0
Requires-Dist: nonebot-plugin-apscheduler>=0.5.0,<1.0.0
Requires-Dist: bilibili-api-python>=17.3.0,<18.0.0
Requires-Dist: bs4>=0.0.2
Requires-Python: >=3.10
Project-URL: Repository, https://github.com/fllesser/nonebot-plugin-parser/tree/resolver2
